minecraft_script/__init__.py
minecraft_script/__main__.py
minecraft_script/common.py
minecraft_script/config.json
minecraft_script/config_utils.py
minecraft_script/errors.py
minecraft_script/shell_commands.py
minecraft_script/text_additions.py
minecraft_script/compiler/__init__.py
minecraft_script/compiler/builtin_functions.py
minecraft_script/compiler/compile_interpreter.py
minecraft_script/compiler/compile_types.py
minecraft_script/compiler/compiler.py
minecraft_script/compiler/build_templates/function_tags.json
minecraft_script/compiler/build_templates/pack.mcmeta
minecraft_script/compiler/build_templates/pack.png
minecraft_script/compiler/build_templates/builtins/command.mcfunction
minecraft_script/compiler/build_templates/builtins/give_item.mcfunction
minecraft_script/compiler/build_templates/builtins/log.mcfunction
minecraft_script/compiler/build_templates/builtins/set_block.mcfunction
minecraft_script/compiler/build_templates/math/add.mcfunction
minecraft_script/compiler/build_templates/math/divide.mcfunction
minecraft_script/compiler/build_templates/math/equals.mcfunction
minecraft_script/compiler/build_templates/math/greater_equals_than.mcfunction
minecraft_script/compiler/build_templates/math/greater_than.mcfunction
minecraft_script/compiler/build_templates/math/less_equals_than.mcfunction
minecraft_script/compiler/build_templates/math/less_than.mcfunction
minecraft_script/compiler/build_templates/math/modulus.mcfunction
minecraft_script/compiler/build_templates/math/multiply.mcfunction
minecraft_script/compiler/build_templates/math/subtract.mcfunction
minecraft_script/compiler/build_templates/math/u_add.mcfunction
minecraft_script/compiler/build_templates/math/u_not.mcfunction
minecraft_script/compiler/build_templates/math/u_subtract.mcfunction
minecraft_script/compiler/build_templates/tags/blocks/no_collision.json
minecraft_script/interpreter/__init__.py
minecraft_script/interpreter/builtin_functions.py
minecraft_script/interpreter/interpreter.py
minecraft_script-0.2.2.dist-info/METADATA
minecraft_script-0.2.2.dist-info/WHEEL
minecraft_script-0.2.2.dist-info/top_level.txt
minecraft_script-0.2.2.dist-info/RECORD
