Metadata-Version: 2.1
Name: minecraft_script
Version: 0.2.2
Summary: Minecraft Script Programming language
Author: Joyful-Bard
Author-email: <christophe@dronne.fr>
Keywords: minecraft,mc,script,language
Classifier: Intended Audience :: Developers
Classifier: Programming Language :: Python :: 3
Classifier: Operating System :: Microsoft :: Windows
